wekatui/__init__.py
wekatui/apNPSApplication.py
wekatui/apNPSApplicationAdvanced.py
wekatui/apNPSApplicationEvents.py
wekatui/apNPSApplicationManaged.py
wekatui/apOptions.py
wekatui/eveventhandler.py
wekatui/fmActionForm.py
wekatui/fmActionFormV2.py
wekatui/fmDataInputForm.py
wekatui/fmFileSelector.py
wekatui/fmForm.py
wekatui/fmFormMultiPage.py
wekatui/fmFormMutt.py
wekatui/fmFormMuttActive.py
wekatui/fmFormWithMenus.py
wekatui/fmPopup.py
wekatui/fm_form_edit_loop.py
wekatui/globals.py
wekatui/muMenu.py
wekatui/muNewMenu.py
wekatui/npysGlobalOptions.py
wekatui/npysNPSFilteredData.py
wekatui/npysThemeManagers.py
wekatui/npysThemes.py
wekatui/npysTree.py
wekatui/npyspmfuncs.py
wekatui/npyssafewrapper.py
wekatui/proto_fm_screen_area.py
wekatui/stdfmemail.py
wekatui/utilNotify.py
wekatui/util_viewhelp.py
wekatui/wgFormControlCheckbox.py
wekatui/wgNMenuDisplay.py
wekatui/wgannotatetextbox.py
wekatui/wgautocomplete.py
wekatui/wgboxwidget.py
wekatui/wgbutton.py
wekatui/wgcheckbox.py
wekatui/wgcombobox.py
wekatui/wgdatecombo.py
wekatui/wgeditmultiline.py
wekatui/wgfilenamecombo.py
wekatui/wggrid.py
wekatui/wggridcoltitles.py
wekatui/wgmonthbox.py
wekatui/wgmultiline.py
wekatui/wgmultilineeditable.py
wekatui/wgmultilinetree.py
wekatui/wgmultilinetreeselectable.py
wekatui/wgmultiselect.py
wekatui/wgmultiselecttree.py
wekatui/wgpassword.py
wekatui/wgselectone.py
wekatui/wgslider.py
wekatui/wgtextbox.py
wekatui/wgtextbox_controlchrs.py
wekatui/wgtextboxunicode.py
wekatui/wgtexttokens.py
wekatui/wgtitlefield.py
wekatui/wgwidget.py
wekatui/wgwidget_proto.py
wekatui/compatibility_code/__init__.py
wekatui/compatibility_code/npysNPSTree.py
wekatui/compatibility_code/oldtreeclasses.py
wekatui-0.1.3.dist-info/LICENCE
wekatui-0.1.3.dist-info/METADATA
wekatui-0.1.3.dist-info/WHEEL
wekatui-0.1.3.dist-info/top_level.txt
wekatui-0.1.3.dist-info/RECORD
