Metadata-Version: 2.1
Name: wekatui
Version: 0.1.3
Summary: A library for creating simple text-based data input screens
Home-page: http://github.com/weka/wekatui/
Author: Vince Fleming
Author-email: vince@weka.io
License: New BSD License
Platform: UNKNOWN
Classifier: Development Status :: 5 - Production/Stable
Classifier: Programming Language :: Python :: 3
Classifier: Programming Language :: Python :: 2.6
Classifier: Programming Language :: Python :: 2.7
Classifier: Environment :: Console
Classifier: Operating System :: POSIX
Classifier: Environment :: Console :: Curses
Classifier: Intended Audience :: Developers
Classifier: License :: OSI Approved :: BSD License
Classifier: Topic :: Terminals
License-File: LICENCE
